tinyjsondb/__init__.py
tinyjsondb/core.py
tinyjsondb/errors.py
tinyjsondb/fields.py
tinyjsondb-0.1.3.dist-info/licenses/LICENSE.md
tinyjsondb-0.1.3.dist-info/METADATA
tinyjsondb-0.1.3.dist-info/WHEEL
tinyjsondb-0.1.3.dist-info/top_level.txt
tinyjsondb-0.1.3.dist-info/RECORD
