Metadata-Version: 2.4
Name: tinyjsondb
Version: 0.1.3
Summary: A lightweight, JSON-based Python ORM library
Author: Waland2
Project-URL: Repository, https://github.com/Waland2/tinyjsondb
Keywords: json,database,orm,tinydb
Classifier: Programming Language :: Python :: 3
Classifier: License :: OSI Approved :: MIT License
Classifier: Operating System :: OS Independent
Requires-Python: >=3.10
License-File: LICENSE.md
Requires-Dist: portalocker>=2.7
Dynamic: license-file
